.class interface abstract Lorg/apache/harmony/luni/internal/reflect/ProxyConstants;
.super Ljava/lang/Object;
.source "ProxyConstants.java"


# static fields
.field public static final AccFinal:I = 0x10

.field public static final AccPrivate:I = 0x2

.field public static final AccProtected:I = 0x4

.field public static final AccPublic:I = 0x1

.field public static final AccStatic:I = 0x8

.field public static final AccSuper:I = 0x20

.field public static final ClassTag:I = 0x7

.field public static final CodeName:[C = null

.field public static final DoubleTag:I = 0x6

.field public static final ExceptionsName:[C = null

.field public static final FieldRefTag:I = 0x9

.field public static final FloatTag:I = 0x4

.field public static final Init:[C = null

.field public static final IntegerTag:I = 0x3

.field public static final InterfaceMethodRefTag:I = 0xb

.field public static final LongTag:I = 0x5

.field public static final MethodRefTag:I = 0xa

.field public static final NameAndTypeTag:I = 0xc

.field public static final OPC_aaload:I = 0x32

.field public static final OPC_aastore:I = 0x53

.field public static final OPC_aconst_null:I = 0x1

.field public static final OPC_aload:I = 0x19

.field public static final OPC_aload_0:I = 0x2a

.field public static final OPC_aload_1:I = 0x2b

.field public static final OPC_aload_2:I = 0x2c

.field public static final OPC_aload_3:I = 0x2d

.field public static final OPC_anewarray:I = 0xbd

.field public static final OPC_areturn:I = 0xb0

.field public static final OPC_arraylength:I = 0xbe

.field public static final OPC_astore:I = 0x3a

.field public static final OPC_astore_0:I = 0x4b

.field public static final OPC_astore_1:I = 0x4c

.field public static final OPC_astore_2:I = 0x4d

.field public static final OPC_astore_3:I = 0x4e

.field public static final OPC_athrow:I = 0xbf

.field public static final OPC_baload:I = 0x33

.field public static final OPC_bastore:I = 0x54

.field public static final OPC_bipush:I = 0x10

.field public static final OPC_caload:I = 0x34

.field public static final OPC_castore:I = 0x55

.field public static final OPC_checkcast:I = 0xc0

.field public static final OPC_d2f:I = 0x90

.field public static final OPC_d2i:I = 0x8e

.field public static final OPC_d2l:I = 0x8f

.field public static final OPC_dadd:I = 0x63

.field public static final OPC_daload:I = 0x31

.field public static final OPC_dastore:I = 0x52

.field public static final OPC_dcmpg:I = 0x98

.field public static final OPC_dcmpl:I = 0x97

.field public static final OPC_dconst_0:I = 0xe

.field public static final OPC_dconst_1:I = 0xf

.field public static final OPC_ddiv:I = 0x6f

.field public static final OPC_dload:I = 0x18

.field public static final OPC_dload_0:I = 0x26

.field public static final OPC_dload_1:I = 0x27

.field public static final OPC_dload_2:I = 0x28

.field public static final OPC_dload_3:I = 0x29

.field public static final OPC_dmul:I = 0x6b

.field public static final OPC_dneg:I = 0x77

.field public static final OPC_drem:I = 0x73

.field public static final OPC_dreturn:I = 0xaf

.field public static final OPC_dstore:I = 0x39

.field public static final OPC_dstore_0:I = 0x47

.field public static final OPC_dstore_1:I = 0x48

.field public static final OPC_dstore_2:I = 0x49

.field public static final OPC_dstore_3:I = 0x4a

.field public static final OPC_dsub:I = 0x67

.field public static final OPC_dup:I = 0x59

.field public static final OPC_dup2:I = 0x5c

.field public static final OPC_dup2_x1:I = 0x5d

.field public static final OPC_dup2_x2:I = 0x5e

.field public static final OPC_dup_x1:I = 0x5a

.field public static final OPC_dup_x2:I = 0x5b

.field public static final OPC_f2d:I = 0x8d

.field public static final OPC_f2i:I = 0x8b

.field public static final OPC_f2l:I = 0x8c

.field public static final OPC_fadd:I = 0x62

.field public static final OPC_faload:I = 0x30

.field public static final OPC_fastore:I = 0x51

.field public static final OPC_fcmpg:I = 0x96

.field public static final OPC_fcmpl:I = 0x95

.field public static final OPC_fconst_0:I = 0xb

.field public static final OPC_fconst_1:I = 0xc

.field public static final OPC_fconst_2:I = 0xd

.field public static final OPC_fdiv:I = 0x6e

.field public static final OPC_fload:I = 0x17

.field public static final OPC_fload_0:I = 0x22

.field public static final OPC_fload_1:I = 0x23

.field public static final OPC_fload_2:I = 0x24

.field public static final OPC_fload_3:I = 0x25

.field public static final OPC_fmul:I = 0x6a

.field public static final OPC_fneg:I = 0x76

.field public static final OPC_frem:I = 0x72

.field public static final OPC_freturn:I = 0xae

.field public static final OPC_fstore:I = 0x38

.field public static final OPC_fstore_0:I = 0x43

.field public static final OPC_fstore_1:I = 0x44

.field public static final OPC_fstore_2:I = 0x45

.field public static final OPC_fstore_3:I = 0x46

.field public static final OPC_fsub:I = 0x66

.field public static final OPC_getfield:I = 0xb4

.field public static final OPC_getstatic:I = 0xb2

.field public static final OPC_goto:I = 0xa7

.field public static final OPC_goto_w:I = 0xc8

.field public static final OPC_i2b:I = 0x91

.field public static final OPC_i2c:I = 0x92

.field public static final OPC_i2d:I = 0x87

.field public static final OPC_i2f:I = 0x86

.field public static final OPC_i2l:I = 0x85

.field public static final OPC_i2s:I = 0x93

.field public static final OPC_iadd:I = 0x60

.field public static final OPC_iaload:I = 0x2e

.field public static final OPC_iand:I = 0x7e

.field public static final OPC_iastore:I = 0x4f

.field public static final OPC_iconst_0:I = 0x3

.field public static final OPC_iconst_1:I = 0x4

.field public static final OPC_iconst_2:I = 0x5

.field public static final OPC_iconst_3:I = 0x6

.field public static final OPC_iconst_4:I = 0x7

.field public static final OPC_iconst_5:I = 0x8

.field public static final OPC_iconst_m1:I = 0x2

.field public static final OPC_idiv:I = 0x6c

.field public static final OPC_if_acmpeq:I = 0xa5

.field public static final OPC_if_acmpne:I = 0xa6

.field public static final OPC_if_icmpeq:I = 0x9f

.field public static final OPC_if_icmpge:I = 0xa2

.field public static final OPC_if_icmpgt:I = 0xa3

.field public static final OPC_if_icmple:I = 0xa4

.field public static final OPC_if_icmplt:I = 0xa1

.field public static final OPC_if_icmpne:I = 0xa0

.field public static final OPC_ifeq:I = 0x99

.field public static final OPC_ifge:I = 0x9c

.field public static final OPC_ifgt:I = 0x9d

.field public static final OPC_ifle:I = 0x9e

.field public static final OPC_iflt:I = 0x9b

.field public static final OPC_ifne:I = 0x9a

.field public static final OPC_ifnonnull:I = 0xc7

.field public static final OPC_ifnull:I = 0xc6

.field public static final OPC_iinc:I = 0x84

.field public static final OPC_iload:I = 0x15

.field public static final OPC_iload_0:I = 0x1a

.field public static final OPC_iload_1:I = 0x1b

.field public static final OPC_iload_2:I = 0x1c

.field public static final OPC_iload_3:I = 0x1d

.field public static final OPC_imul:I = 0x68

.field public static final OPC_ineg:I = 0x74

.field public static final OPC_instanceof:I = 0xc1

.field public static final OPC_invokeinterface:I = 0xb9

.field public static final OPC_invokespecial:I = 0xb7

.field public static final OPC_invokestatic:I = 0xb8

.field public static final OPC_invokevirtual:I = 0xb6

.field public static final OPC_ior:I = 0x80

.field public static final OPC_irem:I = 0x70

.field public static final OPC_ireturn:I = 0xac

.field public static final OPC_ishl:I = 0x78

.field public static final OPC_ishr:I = 0x7a

.field public static final OPC_istore:I = 0x36

.field public static final OPC_istore_0:I = 0x3b

.field public static final OPC_istore_1:I = 0x3c

.field public static final OPC_istore_2:I = 0x3d

.field public static final OPC_istore_3:I = 0x3e

.field public static final OPC_isub:I = 0x64

.field public static final OPC_iushr:I = 0x7c

.field public static final OPC_ixor:I = 0x82

.field public static final OPC_jsr:I = 0xa8

.field public static final OPC_jsr_w:I = 0xc9

.field public static final OPC_l2d:I = 0x8a

.field public static final OPC_l2f:I = 0x89

.field public static final OPC_l2i:I = 0x88

.field public static final OPC_ladd:I = 0x61

.field public static final OPC_laload:I = 0x2f

.field public static final OPC_land:I = 0x7f

.field public static final OPC_lastore:I = 0x50

.field public static final OPC_lcmp:I = 0x94

.field public static final OPC_lconst_0:I = 0x9

.field public static final OPC_lconst_1:I = 0xa

.field public static final OPC_ldc:I = 0x12

.field public static final OPC_ldc2_w:I = 0x14

.field public static final OPC_ldc_w:I = 0x13

.field public static final OPC_ldiv:I = 0x6d

.field public static final OPC_lload:I = 0x16

.field public static final OPC_lload_0:I = 0x1e

.field public static final OPC_lload_1:I = 0x1f

.field public static final OPC_lload_2:I = 0x20

.field public static final OPC_lload_3:I = 0x21

.field public static final OPC_lmul:I = 0x69

.field public static final OPC_lneg:I = 0x75

.field public static final OPC_lookupswitch:I = 0xab

.field public static final OPC_lor:I = 0x81

.field public static final OPC_lrem:I = 0x71

.field public static final OPC_lreturn:I = 0xad

.field public static final OPC_lshl:I = 0x79

.field public static final OPC_lshr:I = 0x7b

.field public static final OPC_lstore:I = 0x37

.field public static final OPC_lstore_0:I = 0x3f

.field public static final OPC_lstore_1:I = 0x40

.field public static final OPC_lstore_2:I = 0x41

.field public static final OPC_lstore_3:I = 0x42

.field public static final OPC_lsub:I = 0x65

.field public static final OPC_lushr:I = 0x7d

.field public static final OPC_lxor:I = 0x83

.field public static final OPC_monitorenter:I = 0xc2

.field public static final OPC_monitorexit:I = 0xc3

.field public static final OPC_multianewarray:I = 0xc5

.field public static final OPC_new:I = 0xbb

.field public static final OPC_newarray:I = 0xbc

.field public static final OPC_nop:I = 0x0

.field public static final OPC_pop:I = 0x57

.field public static final OPC_pop2:I = 0x58

.field public static final OPC_putfield:I = 0xb5

.field public static final OPC_putstatic:I = 0xb3

.field public static final OPC_ret:I = 0xa9

.field public static final OPC_return:I = 0xb1

.field public static final OPC_saload:I = 0x35

.field public static final OPC_sastore:I = 0x56

.field public static final OPC_sipush:I = 0x11

.field public static final OPC_swap:I = 0x5f

.field public static final OPC_tableswitch:I = 0xaa

.field public static final OPC_wide:I = 0xc4

.field public static final StringTag:I = 0x8

.field public static final Utf8Tag:I = 0x1


# direct methods
.method static constructor <clinit>()V
    .locals 1

    .prologue
    .line 21
    const/4 v0, 0x4

    new-array v0, v0, [C

    fill-array-data v0, :array_0

    sput-object v0, Lorg/apache/harmony/luni/internal/reflect/ProxyConstants;->CodeName:[C

    .line 23
    const/16 v0, 0xa

    new-array v0, v0, [C

    fill-array-data v0, :array_1

    sput-object v0, Lorg/apache/harmony/luni/internal/reflect/ProxyConstants;->ExceptionsName:[C

    .line 26
    const/4 v0, 0x6

    new-array v0, v0, [C

    fill-array-data v0, :array_2

    sput-object v0, Lorg/apache/harmony/luni/internal/reflect/ProxyConstants;->Init:[C

    .line 20
    return-void

    .line 21
    :array_0
    .array-data 0x2
        0x43t 0x0t
        0x6ft 0x0t
        0x64t 0x0t
        0x65t 0x0t
    .end array-data

    .line 23
    :array_1
    .array-data 0x2
        0x45t 0x0t
        0x78t 0x0t
        0x63t 0x0t
        0x65t 0x0t
        0x70t 0x0t
        0x74t 0x0t
        0x69t 0x0t
        0x6ft 0x0t
        0x6et 0x0t
        0x73t 0x0t
    .end array-data

    .line 26
    :array_2
    .array-data 0x2
        0x3ct 0x0t
        0x69t 0x0t
        0x6et 0x0t
        0x69t 0x0t
        0x74t 0x0t
        0x3et 0x0t
    .end array-data
.end method
